voice_stream/__init__.py
voice_stream/_substream_iters.py
voice_stream/audio/__init__.py
voice_stream/audio/async_wav_file.py
voice_stream/audio/audio_mp3.py
voice_stream/audio/audio_ogg.py
voice_stream/audio/audio_ops.py
voice_stream/audio/audio_utils.py
voice_stream/audio/audio_webm.py
voice_stream/core.py
voice_stream/events.py
voice_stream/integrations/__init__.py
voice_stream/integrations/_google_endless.py
voice_stream/integrations/fastapi.py
voice_stream/integrations/google.py
voice_stream/integrations/google_utils.py
voice_stream/integrations/langchain.py
voice_stream/integrations/pypi_speech_recognition.py
voice_stream/integrations/quart.py
voice_stream/integrations/twilio.py
voice_stream/langchain_extensions/__init__.py
voice_stream/langchain_extensions/memory.py
voice_stream/langchain_extensions/parsers.py
voice_stream/langchain_extensions/pydantic.py
voice_stream/langchain_extensions/runnables.py
voice_stream/py.typed
voice_stream/queue_with_exception.py
voice_stream/speech_to_text.py
voice_stream/substreams.py
voice_stream/text_to_speech.py
voice_stream/types.py
voice_stream-0.10.0.dist-info/LICENSE
voice_stream-0.10.0.dist-info/METADATA
voice_stream-0.10.0.dist-info/WHEEL
voice_stream-0.10.0.dist-info/RECORD
