Metadata-Version: 2.1
Name: voice-stream
Version: 0.10.0
Summary: A streaming library for creating voice bots using LLMs.  Connects LLMs to speech recognition and speech synthesis APIs.
Home-page: https://github.com/DaveDeCaprio/voice-stream
License: MIT
Keywords: voicebot,genai,twilio,llm
Author: Dave DeCaprio
Author-email: daved@alum.mit.edu
Requires-Python: >=3.9,<4.0
Classifier: Development Status :: 2 - Pre-Alpha
Classifier: Framework :: AsyncIO
Classifier: Intended Audience :: Developers
Classifier: License :: OSI Approved :: MIT License
Classifier: Operating System :: OS Independent
Classifier: Programming Language :: Python :: 3
Classifier: Programming Language :: Python :: 3.9
Classifier: Programming Language :: Python :: 3.10
Classifier: Programming Language :: Python :: 3.11
Classifier: Programming Language :: Python :: 3.12
Classifier: Topic :: Communications :: Conferencing
Classifier: Topic :: Communications :: Telephony
Classifier: Topic :: Multimedia :: Sound/Audio :: Capture/Recording
Classifier: Topic :: Multimedia :: Sound/Audio :: Speech
Classifier: Topic :: Scientific/Engineering :: Artificial Intelligence
Classifier: Typing :: Typed
Provides-Extra: google
Provides-Extra: openai
Provides-Extra: quart
Provides-Extra: quickstart
Provides-Extra: twilio
Requires-Dist: aiofiles (>=22.1.0)
Requires-Dist: asyncstdlib (>=3.9.0)
Requires-Dist: av (>=11.0.0)
Requires-Dist: fastapi (>=0.100.0) ; extra == "quickstart"
Requires-Dist: google-cloud-aiplatform (>=1.38.0) ; extra == "google" or extra == "quickstart"
Requires-Dist: google-cloud-speech (>=2.21.0) ; extra == "google" or extra == "quickstart"
Requires-Dist: google-cloud-texttospeech (>=2.13.0) ; extra == "google" or extra == "quickstart"
Requires-Dist: langchain (>=0.0.333)
Requires-Dist: langchain-google-genai (>=0.0.2) ; extra == "google" or extra == "quickstart"
Requires-Dist: langchain-openai (>=0.0.2) ; extra == "openai"
Requires-Dist: mutagen (>=1.44.0)
Requires-Dist: openai (>=1.7.2) ; extra == "openai"
Requires-Dist: pyaudio (>=0.2.12)
Requires-Dist: pydantic (>=2.2.0)
Requires-Dist: quart (>=0.18.0) ; extra == "quart"
Requires-Dist: tiktoken (>=0.3.3) ; extra == "openai"
Requires-Dist: twilio (>=7.0.0) ; extra == "twilio"
Requires-Dist: uvicorn (>=0.19.0) ; extra == "quickstart"
Requires-Dist: vosk (>=0.3.42)
Requires-Dist: websockets (>=10.0) ; extra == "quickstart"
Project-URL: Documentation, https://voice-stream.readthedocs.io/
Project-URL: Repository, https://github.com/DaveDeCaprio/voice-stream
